bastion_key_client/__init__.py
bastion_key_client/bastion_ansible.py
bastion_key_client/bastion_homedir.py
bastion_key_client/bastion_key.py
bastion_key_client/ansible/README.md
bastion_key_client/ansible/fabric-bastion/ansible.cfg
bastion_key_client/ansible/fabric-bastion/fabric-playbook-ancillary.yml
bastion_key_client/ansible/fabric-bastion/site.yml
bastion_key_client/ansible/fabric-bastion/roles/user/tasks/main.yml
bastion_key_client/ansible/fabric-bastion/roles/user/tasks/user-experimenter.yml
bastion_key_client-1.7.0.data/scripts/client-hammer.py
bastion_key_client-1.7.0.data/scripts/update_bastion_keys.py
bastion_key_client-1.7.0.dist-info/LICENSE
bastion_key_client-1.7.0.dist-info/METADATA
bastion_key_client-1.7.0.dist-info/WHEEL
bastion_key_client-1.7.0.dist-info/top_level.txt
bastion_key_client-1.7.0.dist-info/RECORD
