Metadata-Version: 2.1
Name: bastion_key_client
Version: 1.7.0
Summary: FABRIC Bastion host key rotation utility
Home-page: https://github.com/fabric-testbed/BastionKeyClient
Author: Ilya Baldin, Mert Cevik, Michael Stealey
Classifier: Programming Language :: Python :: 3
Classifier: License :: OSI Approved :: MIT License
Classifier: Operating System :: OS Independent
Requires-Python: >=3.6
License-File: LICENSE
Requires-Dist: attrs ==20.3.0
Requires-Dist: Authlib ==0.15.2
Requires-Dist: bleach ==3.3.0
Requires-Dist: certifi >=2020.12.5
Requires-Dist: cffi ==1.14.4
Requires-Dist: chardet ==4.0.0
Requires-Dist: charset-normalizer ==2.0.10
Requires-Dist: click ==7.1.2
Requires-Dist: colorama ==0.4.4
Requires-Dist: cryptography >=3.3.2
Requires-Dist: docutils ==0.17.1
Requires-Dist: Flask >=1.1.2
Requires-Dist: idna >=2.10
Requires-Dist: importlib-metadata ==3.7.3
Requires-Dist: iniconfig ==1.1.1
Requires-Dist: itsdangerous ==1.1.0
Requires-Dist: Jinja2 >=2.11.3
Requires-Dist: keyring ==21.5.0
Requires-Dist: MarkupSafe ==1.1.1
Requires-Dist: pluggy ==0.13.1
Requires-Dist: pycodestyle ==2.6.0
Requires-Dist: pycparser ==2.20
Requires-Dist: Pygments >=2.9.0
Requires-Dist: pyparsing ==2.4.7
Requires-Dist: python-dateutil ==2.8.2
Requires-Dist: requests >=2.25.1
Requires-Dist: requests-toolbelt ==0.9.1
Requires-Dist: rfc3986 ==1.4.0
Requires-Dist: six ==1.15.0
Requires-Dist: toml ==0.10.2
Requires-Dist: tqdm ==4.54.1
Requires-Dist: urllib3 >=1.26.5
Requires-Dist: webencodings ==0.5.1
Requires-Dist: Werkzeug >=1.0.1
Requires-Dist: zipp ==3.4.0
Requires-Dist: python-dotenv ==0.19.2
Requires-Dist: filelock ==3.4.2
Requires-Dist: ansible >=5.1.0
Requires-Dist: ansible-runner ==2.1.1
